PluginMgr/__init__.py
PyPluginMgr-1.0.2.dist-info/METADATA
PyPluginMgr-1.0.2.dist-info/WHEEL
PyPluginMgr-1.0.2.dist-info/top_level.txt
PyPluginMgr-1.0.2.dist-info/RECORD
