Metadata-Version: 2.1
Name: PyPluginMgr
Version: 1.0.2
Summary: Python Plugin Manager.
Home-page: https://github.com/bschollnick/PyPluginMgr
Author: Benjamin Schollnick
Author-email: Benjamin@Schollnick.net
License: MIT
Keywords: Plugin
Platform: UNKNOWN
Classifier: Environment :: Console
Classifier: Development Status :: 5 - Production/Stable
Classifier: Intended Audience :: Developers
Classifier: Topic :: Software Development
Classifier: License :: OSI Approved :: MIT License
Classifier: Programming Language :: Python :: 3.7
Classifier: Programming Language :: Python :: 3.8
